curripy/README.md
curripy/__generics.py
curripy/__init__.py
curripy/dispatches.py
curripy/dispatches.pyi
curripy/protocols.py
curripy/__bootstrap/README.md
curripy/__bootstrap/builtins_.py
curripy/__bootstrap/builtins_.pyi
curripy/__bootstrap/compose_.py
curripy/__bootstrap/compose_.pyi
curripy/__bootstrap/functools_.py
curripy/__bootstrap/identity_.py
curripy/__bootstrap/identity_.pyi
curripy/__bootstrap/inspect_.py
curripy/__bootstrap/operator_.py
curripy/__bootstrap/operator_.pyi
curripy/__overlays/README.md
curripy/__overlays/builtins_.py
curripy/__overlays/functools_.py
curripy/__overlays/functools_.pyi
curripy/__overlays/operator_.py
curripy/__overlays/operator_.pyi
curripy/builtins_/__init__.py
curripy/builtins_/curried.py
curripy/builtins_/curried.pyi
curripy/builtins_/pointfree.py
curripy/builtins_/pointfree.pyi
curripy/collections_/__init__.py
curripy/collections_/curried.py
curripy/collections_/pointfree.py
curripy/dummies/README.md
curripy/dummies/cls.py
curripy/dummies/func.py
curripy/dummies/obj.py
curripy/dummies/type.py
curripy/dummies/type.pyi
curripy/functools_/__init__.py
curripy/functools_/curried.py
curripy/functools_/pointfree.py
curripy/inspect_/__init__.py
curripy/inspect_/curried.py
curripy/inspect_/pointfree.py
curripy/operator_/__init__.py
curripy/operator_/curried.py
curripy/operator_/pointfree.py
curripy/re_/__init__.py
curripy/re_/curried.py
curripy/re_/pointfree.py
curripy/utils/__init__.py
curripy/utils/compose_.py
curripy/utils/cond.py
curripy/utils/cond.pyi
curripy/utils/curry_.py
curripy/utils/curry_.pyi
curripy/utils/functor.py
curripy/utils/identity_.py
curripy/utils/partial_.py
curripy/utils/partial_.pyi
curripy/utils/raise_.py
curripy/utils/tap_.py
curripy/utils/tap_.pyi
curripy-0.1.1.dist-info/METADATA
curripy-0.1.1.dist-info/WHEEL
curripy-0.1.1.dist-info/licenses/LICENSE.md
curripy-0.1.1.dist-info/RECORD
