Metadata-Version: 2.3
Name: curripy
Version: 0.1.1
Summary: Curried / Point-free versions of the Python standard libraries functions and methods.
Project-URL: Repository, https://github.com/Lehmaning/curripy/
Project-URL: Issues, https://github.com/Lehmaning/curripy/issues
Author-email: Lehmaning <60032845+Lehmaning@users.noreply.github.com>
License-File: LICENSE.md
Requires-Python: >=3.8
Requires-Dist: typing-extensions>=4.12.2
